ansible_lint_gitlab/__init__.py
ansible_lint_gitlab/reporter.py
ansible_lint_gitlab/version.py
ansible_lint_gitlab-1.0.0.dist-info/LICENSE
ansible_lint_gitlab-1.0.0.dist-info/METADATA
ansible_lint_gitlab-1.0.0.dist-info/WHEEL
ansible_lint_gitlab-1.0.0.dist-info/entry_points.txt
ansible_lint_gitlab-1.0.0.dist-info/top_level.txt
ansible_lint_gitlab-1.0.0.dist-info/RECORD
