Metadata-Version: 2.1
Name: ansible-lint-gitlab
Version: 1.0.0
Summary: Converts ansible-lint JSON output into GitLab friendly format (JUnit XML, Codeclimate)
Home-page: https://github.com/devalphakilo/ansible-lint-gitlab
Author: DevAlphaKilo
Author-email: DevAlphaKilo@gmail.com
Keywords: ansible,json,gitlab,ci/cd,xml
Classifier: Programming Language :: Python :: 3
Classifier: License :: OSI Approved :: MIT License
Classifier: Operating System :: OS Independent
Requires-Python: >=3.6
License-File: LICENSE
Requires-Dist: ansible-lint
Requires-Dist: junit-reporter
